minimize/__init__.py
minimize/cli.py
minimize/consts.py
minimize/util.py
test/__init__.py
test/test_source.py
python_minimize-0.0.4.dist-info/LICENSE
python_minimize-0.0.4.dist-info/METADATA
python_minimize-0.0.4.dist-info/WHEEL
python_minimize-0.0.4.dist-info/entry_points.txt
python_minimize-0.0.4.dist-info/top_level.txt
python_minimize-0.0.4.dist-info/RECORD
