Metadata-Version: 2.1
Name: python-minimize
Version: 0.0.4
Summary: Reduce the size of MicroPython projects
Home-page: https://github.com/TSNobleSoftware/minimize
Author: Tom Noble
Author-email: t.s.noble@outlook.com
License: UNKNOWN
Project-URL: Bug Reports, https://github.com/TSNobleSoftware/minimize/issues
Project-URL: Source, https://github.com/TSNobleSoftware/minimize
Keywords: python,micropython,cli
Platform: UNKNOWN
Classifier: Development Status :: 3 - Alpha
Classifier: Intended Audience :: Developers
Classifier: License :: OSI Approved :: Apache Software License
Classifier: Programming Language :: Python :: 3
Classifier: Programming Language :: Python :: 3.8
Classifier: Programming Language :: Python :: Implementation :: MicroPython
Requires-Python: >=3.8
Requires-Dist: click
